[
  {
    "name": "MALAHAYATI",
    "code": "MLH",
    "city": "ACEH BESAR, ACEH",
    "id": 102,
    "dest": "431,266,256,144"
  },
  {
    "name": "KENDAWANGAN",
    "code": "KDW",
    "city": "KETAPANG, KALIMANTAN BARAT",
    "id": 116,
    "dest": ""
  },
  {
    "name": "BELAWAN",
    "code": "BLW",
    "city": "KOTA MEDAN, SUMATERA UTARA",
    "id": 144,
    "dest": "431,266,256"
  },
  {
    "name": "SIBOLGA",
    "code": "SLG",
    "city": "SIBOLGA, SUMATERA UTARA",
    "id": 159,
    "dest": "160,431,336,191,714"
  },
  {
    "name": "GUNUNG SITOLI",
    "code": "GNS",
    "city": "GUNUNGSITOLI, SUMATERA UTARA",
    "id": 160,
    "dest": "431,336,191,714,159"
  },
  {
    "name": "TELUK BAYUR",
    "code": "TBY",
    "city": "PADANG, SUMATERA BARAT",
    "id": 191,
    "dest": "160,431,336,191,714,159"
  },
  {
    "name": "MIDAI",
    "code": "MDI",
    "city": "NATUNA, KEPULAUAN RIAU",
    "id": 246,
    "dest": "322,431,252,269,563,251,725,255,246,714"
  },
  {
    "name": "KIJANG",
    "code": "KJG",
    "city": "KOTA TANJUNG PINANG, KEPULAUAN RIAU",
    "id": 251,
    "dest": "322,431,252,269,563,251,725,255,246,714"
  },
  {
    "name": "TAREMPA",
    "code": "TRP",
    "city": "KEPULAUAN ANAMBAS, KEPULAUAN RIAU",
    "id": 252,
    "dest": "322,431,252,269,563,251,725,255,246,714"
  },
  {
    "name": "SERASAN",
    "code": "SRN",
    "city": "NATUNA, KEPULAUAN RIAU",
    "id": 255,
    "dest": "322,431,252,269,563,251,725,255,246,714"
  },
  {
    "name": "PULAU BATAM",
    "code": "BTM",
    "city": "KOTA BATAM, KEPULAUAN RIAU",
    "id": 256,
    "dest": "431,266,256,144"
  },
  {
    "name": "TANJUNG BALAI KARIMUN",
    "code": "TBI",
    "city": "KARIMUN, KEPULAUAN RIAU",
    "id": 266,
    "dest": "431,266,256,144"
  },
  {
    "name": "LETUNG",
    "code": "LTG",
    "city": "KEPULAUAN ANAMBAS, KEPULAUAN RIAU",
    "id": 269,
    "dest": "322,431,252,269,563,251,725,255,246,714"
  },
  {
    "name": "BELINYU",
    "code": "BLN",
    "city": "BANGKA, KEPULAUAN BANGKA BELITUNG",
    "id": 322,
    "dest": "322,431,252,269,563,251,725,255,246,714"
  },
  {
    "name": "PANGKALAN BUN",
    "code": "PLB",
    "city": "KOTAWARINGIN BARAT, KALIMANTAN TENGAH",
    "id": 324,
    "dest": ""
  },
  {
    "name": "TANJUNG PANDAN",
    "code": "TPD",
    "city": "KEPULAUAN BANGKA BELITUNG, BELITUNG",
    "id": 336,
    "dest": "431,336,494,563,747,714,773"
  },
  {
    "name": "SADAI",
    "code": "SDI",
    "city": "BANGKA SELATAN, KEPULAUAN BANGKA BELITUNG",
    "id": 338,
    "dest": ""
  },
  {
    "name": "PANJANG",
    "code": "PNJ",
    "city": "BANDAR LAMPUNG, LAMPUNG",
    "id": 395,
    "dest": "395,431,433"
  },
  {
    "name": "TANJUNG PRIOK",
    "code": "TPK",
    "city": "JAKARTA UTARA, DKI JAKARTA",
    "id": 431,
    "dest": "322,973,951,976,777,431,974,949,977,266,252,269,944,336,975,946,256,921,835,893,144,494,563,251,942,747,947,972,982,246,725,255,714,971,773,981"
  },
  {
    "name": "PATIMBAN",
    "code": "PTM",
    "city": "SUBANG, JAWA BARAT",
    "id": 464,
    "dest": "431"
  },
  {
    "name": "SEMARANG",
    "code": "SMG",
    "city": "KOTA SEMARANG, JAWA TENGAH",
    "id": 494,
    "dest": "431,496,336,494,563,747,746,714,773"
  },
  {
    "name": "KARIMUN JAWA",
    "code": "KRJ",
    "city": "KABUPATEN JEPARA, JAWA TENGAH",
    "id": 496,
    "dest": "494,563,747,746"
  },
  {
    "name": "SURABAYA",
    "code": "SBY",
    "city": "KOTA SURABAYA, JAWA TIMUR",
    "id": 563,
    "dest": "694,948,908,322,973,655,951,929,684,976,777,925,431,974,949,496,977,269,252,944,336,975,946,803,921,835,898,613,893,863,892,494,563,251,942,747,746,681,651,947,950,662,972,979,983,982,246,255,725,714,696,971,685,773,981,923,061"
  },
  {
    "name": "BAWEAN",
    "code": "BWN",
    "city": "GRESIK, JAWA TIMUR",
    "id": 590,
    "dest": ""
  },
  {
    "name": "BENOA/DENPASAR",
    "code": "BNA",
    "city": "KOTA DENPASAR, BALI",
    "id": 613,
    "dest": "694,948,868,655,929,684,841,949,924,922,944,946,921,835,898,613,893,892,563,747,681,106,651,891,950,662,979,983,696,685,923"
  },
  {
    "name": "AMPENAN/LEMBAR",
    "code": "AMP",
    "city": "LOMBOK BARAT, NUSA TENGGARA BARAT",
    "id": 651,
    "dest": "868,655,841,924,922,921,835,898,613,893,892,563,106,651,662,685,773"
  },
  {
    "name": "BIMA",
    "code": "BMA",
    "city": "BIMA, NUSA TENGGARA BARAT",
    "id": 655,
    "dest": "694,948,868,655,929,684,841,949,924,922,944,946,921,835,898,613,893,892,563,747,681,106,651,891,950,662,979,983,696,685,923"
  },
  {
    "name": "LABUAN BAJO",
    "code": "LBJ",
    "city": "MANGGARAI BARAT, NUSA TENGGARA TIMUR",
    "id": 662,
    "dest": "948,868,655,929,684,841,949,924,922,944,946,921,835,898,613,893,892,563,681,106,651,891,950,662,979,983,685,923"
  },
  {
    "name": "MARAPOKOT",
    "code": "MOT",
    "city": "NAGEKO, NUSA TENGGARA TIMUR",
    "id": 663,
    "dest": ""
  },
  {
    "name": "REO",
    "code": "REO",
    "city": "MANGGARAI, NUSA TENGGARA TIMUR",
    "id": 672,
    "dest": "655,684,893,681,662,673,685,773"
  },
  {
    "name": "WAIKELO",
    "code": "WIO",
    "city": "SUMBA BARAT DAYA, NUSA TENGGARA TIMUR",
    "id": 673,
    "dest": "694,655,684,893,681,662,673,685,773"
  },
  {
    "name": "KUPANG",
    "code": "KPG",
    "city": "KUPANG, NUSA TENGGARA TIMUR",
    "id": 681,
    "dest": "694,948,655,684,949,944,946,803,921,613,893,892,563,747,681,688,950,979,983,809,696,683,971,685,808,923"
  },
  {
    "name": "MAUMERE",
    "code": "MMR",
    "city": "SIKA, NUSA TENGGARA TIMUR",
    "id": 683,
    "dest": "694,948,687,949,944,946,803,921,893,863,892,681,688,950,979,983,809,683,971,808,923"
  },
  {
    "name": "ENDE",
    "code": "END",
    "city": "ENDE, NUSA TENGGARA TIMUR",
    "id": 684,
    "dest": "694,655,684,613,563,747,681,696,685"
  },
  {
    "name": "WAINGAPU",
    "code": "WGP",
    "city": "SUMBA TIMUR, NUSA TENGGARA TIMUR",
    "id": 685,
    "dest": "694,655,684,898,613,892,563,747,681,651,696,685,773"
  },
  {
    "name": "LARANTUKA",
    "code": "LTK",
    "city": "FLORES TIMUR, NUSA TENGGARA TIMUR",
    "id": 687,
    "dest": "803,921,893,863,892,809,808"
  },
  {
    "name": "LEWOLEBA",
    "code": "LWB",
    "city": "LEMBATA, NUSA TENGGARA TIMUR",
    "id": 688,
    "dest": "694,948,949,944,946,803,921,893,892,681,688,950,979,983,809,683,971,808,923"
  },
  {
    "name": "KALABAHI",
    "code": "KBH",
    "city": "ALOR, NUSA TENGGARA TIMUR",
    "id": 694,
    "dest": "694,948,655,684,949,944,946,921,613,563,747,681,688,950,979,983,696,683,971,685,923"
  },
  {
    "name": "ROTE",
    "code": "ROT",
    "city": "ROTENDAO, NUSA TENGGARA TIMUR",
    "id": 696,
    "dest": "694,655,684,613,563,747,681,685"
  },
  {
    "name": "SEBA, SABU",
    "code": "ISA",
    "city": "SABU RAIJUA, NUSA TENGGARA TIMUR",
    "id": 697,
    "dest": "694,655,893,681,662,696,773"
  },
  {
    "name": "PONTIANAK",
    "code": "PTK",
    "city": "PONTIANAK, KALIMANTAN BARAT",
    "id": 714,
    "dest": "322,431,252,269,336,494,563,251,747,246,255,725,714,773"
  },
  {
    "name": "KETAPANG",
    "code": "IKL",
    "city": "SUMENEP, JAWA TIMUR",
    "id": 715,
    "dest": ""
  },
  {
    "name": "NATUNA",
    "code": "NTA",
    "city": "NATUNA, KEPULAUAN RIAU",
    "id": 725,
    "dest": "322,431,252,269,563,251,725,255,246,714"
  },
  {
    "name": "SAMPIT",
    "code": "SPT",
    "city": "KOTAWARINGIN TIMUR, KALIMANTAN TENGAH",
    "id": 746,
    "dest": "496,494,563,747,746"
  },
  {
    "name": "KUMAI",
    "code": "KMI",
    "city": "KOTAWARINGIN BARAT, KALIMANTAN TENGAH",
    "id": 747,
    "dest": "694,655,684,431,496,336,613,494,563,747,746,681,714,696,685,773"
  },
  {
    "name": "BATULICIN",
    "code": "BLC",
    "city": "TANAH BUMBU, KALIMANTAN SELATAN",
    "id": 773,
    "dest": "431,336,898,892,494,563,747,651,714,685,773"
  },
  {
    "name": "JAILOLO",
    "code": "JAI",
    "city": "HALMAHERA BARAT, MALUKU UTARA",
    "id": 777,
    "dest": "951,777,431,946,921,835,893,563,942"
  },
  {
    "name": "BALIKPAPAN",
    "code": "BPP",
    "city": "KOTA BALIKPAPAN, KALIMANTAN TIMUR",
    "id": 803,
    "dest": "687,974,975,803,921,835,893,863,892,563,942,681,688,972,982,809,683,971,808,981"
  },
  {
    "name": "TARAKAN",
    "code": "TRK",
    "city": "TARAKAN, KALIMANTAN TIMUR",
    "id": 808,
    "dest": "687,803,921,893,863,892,681,688,809,683,808"
  },
  {
    "name": "NUNUKAN",
    "code": "NNK",
    "city": "NUNUKAN, KALIMANTAN TIMUR",
    "id": 809,
    "dest": "687,803,921,893,863,892,681,688,809,683,808"
  },
  {
    "name": "KAHAKITANG",
    "code": "KKG",
    "city": "KEPULAUAN SANGIHE, SULAWESI UTARA",
    "id": 829,
    "dest": "951,841,928,829,836,844,845,846,946,835,942,840,839"
  },
  {
    "name": "BITUNG",
    "code": "BTG",
    "city": "KOTA BITUNG, SULAWESI UTARA",
    "id": 835,
    "dest": "948,868,908,973,655,951,976,841,777,925,431,974,949,924,928,977,922,944,975,946,803,921,835,613,893,863,563,942,106,651,947,662,972,979,983,982,955,971,981,889"
  },
  {
    "name": "TAHUNA",
    "code": "THA",
    "city": "KEPULAUAN SANGIHE, SULAWESI UTARA",
    "id": 836,
    "dest": "951,841,928,829,836,844,845,846,946,835,942,840,839"
  },
  {
    "name": "WAKAI, TOGIAN",
    "code": "WAK",
    "city": "TOJO UNA-UNA, SULAWESI TENGAH",
    "id": 839,
    "dest": "951,841,928,946,835,942,840,839"
  },
  {
    "name": "POSO",
    "code": "PSJ",
    "city": "POSO, SULAWESI TENGAH",
    "id": 840,
    "dest": "951,841,928,946,835,942,839"
  },
  {
    "name": "GORONTALO",
    "code": "GTO",
    "city": "GORONTALO, GORONTALO",
    "id": 841,
    "dest": "868,655,841,924,922,921,835,613,893,106,651,662"
  },
  {
    "name": "LIRUNG",
    "code": "LRG",
    "city": "KEPULAUAN TALAUD, SULAWESI UTARA",
    "id": 844,
    "dest": "951,841,928,829,836,844,845,846,946,835,942,840,839"
  },
  {
    "name": "KARATUNG",
    "code": "KTN",
    "city": "KEPULAUAN TALAUD, SULAWESI UTARA",
    "id": 845,
    "dest": "951,841,928,829,836,844,845,846,946,835,942,840,839"
  },
  {
    "name": "MIANGAS",
    "code": "MGS",
    "city": "KEPULAUAN TALAUD, SULAWESI UTARA",
    "id": 846,
    "dest": "951,841,928,829,836,844,845,946,835,942,840,839"
  },
  {
    "name": "TOLI",
    "code": "TLI",
    "city": "TOLI-TOLI, SULAWESI TENGAH",
    "id": 861,
    "dest": ""
  },
  {
    "name": "PANTOLOAN",
    "code": "PTL",
    "city": "KOTA PALU, SULAWESI TENGAH",
    "id": 863,
    "dest": "687,974,975,803,921,835,893,863,892,563,942,972,982,809,683,971,808,981"
  },
  {
    "name": "KOLONEDALE",
    "code": "KAN",
    "city": "MOROWALI, SULAWESI TENGAH",
    "id": 867,
    "dest": ""
  },
  {
    "name": "LUWUK",
    "code": "LWK",
    "city": "BANGGAI, SULAWESI TENGAH",
    "id": 868,
    "dest": "868,655,841,924,922,921,835,613,893,106,651,662"
  },
  {
    "name": "TIDORE",
    "code": "TDR",
    "city": "TIDORE KEPULAUAN, MALUKU UTARA",
    "id": 889,
    "dest": "948,976,949,977,835,979,983,971,889"
  },
  {
    "name": "AWERANGE",
    "code": "AWR",
    "city": "LUWU TIMUR, PAPUA",
    "id": 891,
    "dest": "655,898,613,893,892,891,662"
  },
  {
    "name": "PARE",
    "code": "PRE",
    "city": "KOTA PARE-PARE, SULAWESI SELATAN",
    "id": 892,
    "dest": "655,684,687,803,921,898,613,893,863,892,563,681,688,651,891,662,809,683,685,773,808"
  },
  {
    "name": "MAKASSAR",
    "code": "MKS",
    "city": "KOTA MAKASAR, SULAWESI SELATAN",
    "id": 893,
    "dest": "948,868,908,973,655,951,929,684,976,687,841,777,925,431,974,949,924,977,922,944,975,946,803,921,835,898,613,893,863,892,563,942,681,688,106,651,891,947,950,662,972,979,983,982,809,683,971,685,808,981,923,061"
  },
  {
    "name": "BELANG",
    "code": "BEL",
    "city": "MAMUJU, SULAWESI BARAT",
    "id": 894,
    "dest": ""
  },
  {
    "name": "BONTANG",
    "code": "BON",
    "city": "KOTA BONTANG, KALIMANTAN TIMUR",
    "id": 898,
    "dest": "655,684,898,613,893,892,563,681,651,891,662,685,773"
  },
  {
    "name": "BANGGAI",
    "code": "BGI",
    "city": "BANGGAI KEPULAUAN, SULAWESI TENGAH",
    "id": 908,
    "dest": "908,973,925,974,921,835,893,563,942,972,971,981"
  },
  {
    "name": "AMURANG",
    "code": "AUG",
    "city": "MINAHASA SELATAN, SULAWESI UTARA",
    "id": 920,
    "dest": ""
  },
  {
    "name": "BAU",
    "code": "BAU",
    "city": "KOTA BAU-BAU, SULAWESI TENGGARA",
    "id": 921,
    "dest": "694,948,868,908,973,655,951,929,976,687,841,777,925,431,974,949,924,977,922,944,975,946,803,921,835,613,893,863,892,563,942,681,688,106,651,947,950,662,972,979,983,982,809,683,971,808,981,923,061"
  },
  {
    "name": "KENDARI",
    "code": "KDR",
    "city": "KENDARI, SULAWESI TENGGARA",
    "id": 922,
    "dest": "868,655,841,924,922,921,835,613,893,106,651,662"
  },
  {
    "name": "WANCI",
    "code": "WNC",
    "city": "WAKATOBI, SULAWESI TENGGARA",
    "id": 923,
    "dest": "694,948,655,929,949,944,946,921,613,893,563,681,688,950,662,979,983,683,971,923"
  },
  {
    "name": "RAHA",
    "code": "RHA",
    "city": "KABUPATEN MUNA, SULAWESI TENGGARA",
    "id": 924,
    "dest": "868,655,841,924,922,921,835,613,893,106,651,662"
  },
  {
    "name": "BABANG ( BACAN )",
    "code": "BBG",
    "city": "HALMAHERA SELATAN, MALUKU UTARA",
    "id": 925,
    "dest": "908,973,951,976,925,974,928,946,921,835,893,563,942,947,972,955,971,981"
  },
  {
    "name": "MERANTI/DORAK",
    "code": "MRT",
    "city": "PULAU MERANTI, RIAU",
    "id": 926,
    "dest": ""
  },
  {
    "name": "SANANA",
    "code": "SNN",
    "city": "KABUPATEN SULA, MALUKU UTARA",
    "id": 928,
    "dest": "951,976,925,928,946,835,942,947,955"
  },
  {
    "name": "NAMROLE",
    "code": "NRL",
    "city": "BURU SELATAN, MALUKU",
    "id": 929,
    "dest": "948,655,929,949,944,946,921,613,893,563,950,662,979,983,923"
  },
  {
    "name": "TOBELO",
    "code": "TBO",
    "city": "HALMAHERA UTARA, MALUKU UTARA",
    "id": 941,
    "dest": ""
  },
  {
    "name": "TERNATE",
    "code": "TNT",
    "city": "KOTA TERNATE, MALUKU UTARA",
    "id": 942,
    "dest": "948,908,973,951,976,777,925,431,974,949,928,944,975,946,803,921,835,893,863,563,942,947,972,979,983,982,955,971,981"
  },
  {
    "name": "DOBO",
    "code": "DBO",
    "city": "KEPULAUAN ARU, MALUKU",
    "id": 944,
    "dest": "694,948,655,929,976,431,949,977,944,946,921,835,613,893,563,942,681,688,947,950,662,979,983,683,971,923"
  },
  {
    "name": "AMBON",
    "code": "AMB",
    "city": "KOTA AMBON, MALUKU",
    "id": 946,
    "dest": "694,948,655,951,929,976,777,925,431,974,949,928,977,944,975,946,921,835,613,893,563,942,681,688,947,950,662,972,979,983,982,955,683,971,923,061"
  },
  {
    "name": "BANDA",
    "code": "BDA",
    "city": "MALUKU TENGAH, MALUKU",
    "id": 947,
    "dest": "951,976,925,431,949,928,977,944,946,921,835,893,563,942,947,955"
  },
  {
    "name": "AGATS",
    "code": "AGT",
    "city": "ASMAT, PAPUA",
    "id": 948,
    "dest": "694,948,655,929,976,949,977,944,946,921,835,613,893,563,942,681,688,950,662,979,983,683,971,889,923"
  },
  {
    "name": "TUAL",
    "code": "TUL",
    "city": "KAB. TUAL, MALUKU",
    "id": 949,
    "dest": "694,948,655,929,976,431,949,977,944,946,921,835,613,893,563,942,681,688,947,950,662,979,983,683,971,889,923"
  },
  {
    "name": "SAUMLAKI",
    "code": "SML",
    "city": "MALUKU TENGGARA BARAT, MALUKU",
    "id": 950,
    "dest": "694,948,655,929,949,944,946,921,613,893,563,681,688,950,662,979,983,683,971,923"
  },
  {
    "name": "NAMLEA",
    "code": "NLA",
    "city": "BURU, MALUKU",
    "id": 951,
    "dest": "951,976,777,925,431,974,928,975,946,921,835,893,563,942,947,972,982,955,971,061"
  },
  {
    "name": "AMAHAI",
    "code": "AHI",
    "city": "MALUKU TENGAH, MALUKU",
    "id": 952,
    "dest": ""
  },
  {
    "name": "GESER",
    "code": "GS",
    "city": "SERAM BAGIAN TIMUR, MALUKU",
    "id": 955,
    "dest": "951,976,925,928,946,835,942,947,955"
  },
  {
    "name": "KISAR",
    "code": "KXR",
    "city": "MALUKU BARAT DAYA, MALUKU",
    "id": 956,
    "dest": "946,958,959,947,950,955"
  },
  {
    "name": "LARAT",
    "code": "LRT",
    "city": "MALUKU TENGGARA BARAT, MALUKU",
    "id": 957,
    "dest": ""
  },
  {
    "name": "TEPA",
    "code": "TPA",
    "city": "MALUKU BARAT DAYA, MALUKU",
    "id": 958,
    "dest": "946,959,956,958,947,950,955"
  },
  {
    "name": "MOA",
    "code": "KWU",
    "city": "MALUKU BARAT DAYA, MALUKU",
    "id": 959,
    "dest": "946,959,956,958,947,950,955"
  },
  {
    "name": "SORONG",
    "code": "SRG",
    "city": "SORONG, PAPUA BARAT",
    "id": 971,
    "dest": "694,948,908,973,951,976,925,431,974,949,977,944,975,946,803,921,835,893,863,563,942,681,688,950,972,979,983,982,683,971,981,889,923,061"
  },
  {
    "name": "MANOKWARI",
    "code": "MAN",
    "city": "MANOKWARI, PAPUA BARAT",
    "id": 972,
    "dest": "908,973,951,925,431,974,975,946,803,921,835,893,863,563,942,972,982,971,981,061"
  },
  {
    "name": "BIAK",
    "code": "BIK",
    "city": "BIAK NUMFOR, PAPUA",
    "id": 973,
    "dest": "908,973,925,431,974,921,835,893,563,942,972,971,981"
  },
  {
    "name": "JAYAPURA",
    "code": "JPR",
    "city": "JAYAPURA, PAPUA",
    "id": 974,
    "dest": "908,973,951,925,431,975,946,803,921,835,893,863,563,942,972,982,971,981,061"
  },
  {
    "name": "SERUI",
    "code": "SRI",
    "city": "KEPULAUAN YAPEN, PAPUA",
    "id": 975,
    "dest": "951,431,974,975,946,803,921,835,893,863,563,942,972,982,971,981,061"
  },
  {
    "name": "FAK",
    "code": "FAK",
    "city": "FAKFAK, PAPUA BARAT",
    "id": 976,
    "dest": "948,951,976,925,431,949,928,977,944,946,921,835,893,563,942,947,979,983,955,971,889"
  },
  {
    "name": "KAIMANA",
    "code": "KMN",
    "city": "KAIMANA, PAPUA BARAT",
    "id": 977,
    "dest": "948,976,431,949,977,944,946,921,835,893,563,947,979,983,971,889"
  },
  {
    "name": "MERAUKE",
    "code": "MRK",
    "city": "MERAUKE, PAPUA",
    "id": 979,
    "dest": "694,948,655,929,976,949,977,944,946,921,835,613,893,563,942,681,688,950,662,983,683,971,889,923"
  },
  {
    "name": "WASIOR",
    "code": "WSR",
    "city": "TELUK WONDAMA, PAPUA BARAT",
    "id": 981,
    "dest": "908,925,431,974,803,921,835,893,863,563,942,972,982,971,981"
  },
  {
    "name": "NABIRE",
    "code": "NBR",
    "city": "NABIRE, PAPUA",
    "id": 982,
    "dest": "951,431,974,975,946,803,921,835,893,863,563,942,972,982,971,981,061"
  },
  {
    "name": "TIMIKA",
    "code": "TMK",
    "city": "MIMIKA, PAPUA",
    "id": 983,
    "dest": "694,948,655,929,976,949,977,944,946,921,835,613,893,563,942,681,688,950,662,979,983,683,971,889,923"
  },
  {
    "name": "KOTABARU",
    "code": "KTB",
    "city": "BARU, KALIMANTAN SELATAN",
    "id": 996,
    "dest": ""
  },
  {
    "name": "JAILOLO",
    "code": "JIO",
    "city": "HALMAHERA BARAT, MALUKU UTARA",
    "id": 1466,
    "dest": ""
  }
]